pygama/__init__.py
pygama/_version.py
pygama/cli.py
pygama/logging.py
pygama/utils.py
pygama/evt/__init__.py
pygama/evt/aggregators.py
pygama/evt/build_evt.py
pygama/evt/build_tcm.py
pygama/evt/tcm.py
pygama/evt/utils.py
pygama/evt/modules/__init__.py
pygama/evt/modules/geds.py
pygama/evt/modules/larveto.py
pygama/evt/modules/legend.py
pygama/evt/modules/spms.py
pygama/evt/modules/xtalk.py
pygama/flow/__init__.py
pygama/flow/data_loader.py
pygama/flow/file_db.py
pygama/flow/utils.py
pygama/hit/__init__.py
pygama/hit/build_hit.py
pygama/math/__init__.py
pygama/math/binned_fitting.py
pygama/math/distributions.py
pygama/math/histogram.py
pygama/math/hpge_peak_fitting.py
pygama/math/least_squares.py
pygama/math/unbinned_fitting.py
pygama/math/units.py
pygama/math/utils.py
pygama/math/functions/__init__.py
pygama/math/functions/crystal_ball.py
pygama/math/functions/error_function.py
pygama/math/functions/exgauss.py
pygama/math/functions/exponential.py
pygama/math/functions/gauss.py
pygama/math/functions/gauss_on_exgauss.py
pygama/math/functions/gauss_on_exponential.py
pygama/math/functions/gauss_on_linear.py
pygama/math/functions/gauss_on_step.py
pygama/math/functions/gauss_on_uniform.py
pygama/math/functions/hpge_peak.py
pygama/math/functions/linear.py
pygama/math/functions/moyal.py
pygama/math/functions/poisson.py
pygama/math/functions/polynomial.py
pygama/math/functions/pygama_continuous.py
pygama/math/functions/step.py
pygama/math/functions/sum_dists.py
pygama/math/functions/triple_gauss_on_double_step.py
pygama/math/functions/uniform.py
pygama/pargen/AoE_cal.py
pygama/pargen/__init__.py
pygama/pargen/data_cleaning.py
pygama/pargen/dplms_ge_dict.py
pygama/pargen/dsp_optimize.py
pygama/pargen/energy_cal.py
pygama/pargen/energy_optimisation.py
pygama/pargen/lq_cal.py
pygama/pargen/noise_optimization.py
pygama/pargen/pz_correct.py
pygama/pargen/survival_fractions.py
pygama/pargen/utils.py
pygama-2.3.0.dist-info/licenses/LICENSE
pygama-2.3.0.dist-info/METADATA
pygama-2.3.0.dist-info/WHEEL
pygama-2.3.0.dist-info/entry_points.txt
pygama-2.3.0.dist-info/top_level.txt
pygama-2.3.0.dist-info/RECORD
