Metadata-Version: 2.4
Name: pygama
Version: 2.3.0
Summary: Python package for data processing and analysis
Author: The LEGEND collaboration
Maintainer: The LEGEND collaboration
Project-URL: Homepage, https://github.com/legend-exp/pygama
Project-URL: Bug Tracker, https://github.com/legend-exp/pygama/issues
Project-URL: Discussions, https://github.com/legend-exp/pygama/discussions
Project-URL: Changelog, https://github.com/legend-exp/pygama/releases
Classifier: Development Status :: 4 - Beta
Classifier: Intended Audience :: Developers
Classifier: Intended Audience :: Science/Research
Classifier: License :: OSI Approved :: GNU General Public License v3 (GPLv3)
Classifier: Operating System :: MacOS
Classifier: Operating System :: POSIX
Classifier: Operating System :: Unix
Classifier: Programming Language :: Python
Classifier: Programming Language :: Python :: 3
Classifier: Programming Language :: Python :: 3 :: Only
Classifier: Topic :: Scientific/Engineering
Requires-Python: >=3.9
License-File: LICENSE
Requires-Dist: hist
Requires-Dist: colorlog
Requires-Dist: dbetto
Requires-Dist: dspeed>=2.0
Requires-Dist: h5py>=3.2
Requires-Dist: iminuit
Requires-Dist: legend-pydataobj>=1.16
Requires-Dist: pylegendmeta>=0.9
Requires-Dist: matplotlib
Requires-Dist: numba!=0.53.*,!=0.54.*,!=0.57
Requires-Dist: numpy>=1.21
Requires-Dist: pandas>=1.4.4
Requires-Dist: tables
Requires-Dist: numpy==1.26.4; python_version == "3.9"
Requires-Dist: pandas==1.5.3; python_version == "3.9"
Requires-Dist: tables==3.9.2; python_version == "3.9"
Requires-Dist: pint
Requires-Dist: pyyaml
Requires-Dist: scikit-learn
Requires-Dist: scipy>=1.0.1
Requires-Dist: tqdm>=4.66
Provides-Extra: all
Requires-Dist: pygama[docs,test]; extra == "all"
Provides-Extra: docs
Requires-Dist: furo; extra == "docs"
Requires-Dist: jupyter; extra == "docs"
Requires-Dist: myst-parser; extra == "docs"
Requires-Dist: nbsphinx; extra == "docs"
Requires-Dist: sphinx; extra == "docs"
Requires-Dist: sphinx-copybutton; extra == "docs"
Requires-Dist: sphinx-inline-tabs; extra == "docs"
Provides-Extra: test
Requires-Dist: pre-commit; extra == "test"
Requires-Dist: pylegendtestdata; extra == "test"
Requires-Dist: pytest>=6.0; extra == "test"
Requires-Dist: pytest-cov; extra == "test"
Dynamic: license-file
